ragas_wj/__init__.py
ragas_wj/_analytics.py
ragas_wj/_version.py
ragas_wj/async_utils.py
ragas_wj/callbacks.py
ragas_wj/cost.py
ragas_wj/dataset_schema.py
ragas_wj/evaluation.py
ragas_wj/exceptions.py
ragas_wj/executor.py
ragas_wj/messages.py
ragas_wj/run_config.py
ragas_wj/utils.py
ragas_wj/validation.py
ragas_wj/embeddings/__init__.py
ragas_wj/embeddings/base.py
ragas_wj/experimental/__init__.py
ragas_wj/integrations/__init__.py
ragas_wj/integrations/helicone.py
ragas_wj/integrations/langchain.py
ragas_wj/integrations/langgraph.py
ragas_wj/integrations/langsmith.py
ragas_wj/integrations/llama_index.py
ragas_wj/integrations/opik.py
ragas_wj/llms/__init__.py
ragas_wj/llms/base.py
ragas_wj/metrics/__init__.py
ragas_wj/metrics/_answer_correctness.py
ragas_wj/metrics/_answer_relevance.py
ragas_wj/metrics/_answer_similarity.py
ragas_wj/metrics/_aspect_critic.py
ragas_wj/metrics/_bleu_score.py
ragas_wj/metrics/_context_entities_recall.py
ragas_wj/metrics/_context_precision.py
ragas_wj/metrics/_context_recall.py
ragas_wj/metrics/_datacompy_score.py
ragas_wj/metrics/_domain_specific_rubrics.py
ragas_wj/metrics/_factual_correctness.py
ragas_wj/metrics/_faithfulness.py
ragas_wj/metrics/_goal_accuracy.py
ragas_wj/metrics/_instance_specific_rubrics.py
ragas_wj/metrics/_multi_modal_faithfulness.py
ragas_wj/metrics/_multi_modal_relevance.py
ragas_wj/metrics/_noise_sensitivity.py
ragas_wj/metrics/_rouge_score.py
ragas_wj/metrics/_simple_criteria.py
ragas_wj/metrics/_sql_semantic_equivalence.py
ragas_wj/metrics/_string.py
ragas_wj/metrics/_summarization.py
ragas_wj/metrics/_tool_call_accuracy.py
ragas_wj/metrics/_topic_adherence.py
ragas_wj/metrics/base.py
ragas_wj/metrics/utils.py
ragas_wj/prompt/__init__.py
ragas_wj/prompt/base.py
ragas_wj/prompt/mixin.py
ragas_wj/prompt/multi_modal_prompt.py
ragas_wj/prompt/pydantic_prompt.py
ragas_wj/prompt/utils.py
ragas_wj/testset/__init__.py
ragas_wj/testset/graph.py
ragas_wj/testset/graph_queries.py
ragas_wj/testset/persona.py
ragas_wj-0.1.4.dist-info/METADATA
ragas_wj-0.1.4.dist-info/WHEEL
ragas_wj-0.1.4.dist-info/top_level.txt
ragas_wj-0.1.4.dist-info/RECORD
